AUTHORS.rst
CONTRIBUTING.rst
HISTORY.rst
LICENSE.txt
MANIFEST.in
README.rst
_version.py
pyproject.toml
setup.cfg
setup.py
versioneer.py
cybuffer.egg-info/PKG-INFO
cybuffer.egg-info/SOURCES.txt
cybuffer.egg-info/dependency_links.txt
cybuffer.egg-info/not-zip-safe
cybuffer.egg-info/top_level.txt
docs/Makefile
docs/api.rst
docs/authors.rst
docs/conf.py
docs/contributing.rst
docs/history.rst
docs/index.rst
docs/installation.rst
docs/make.bat
docs/readme.rst
docs/usage.rst
src/cybuffer.pxd
src/cybuffer.pyx
tests/__init__.py
tests/test_cybuffer.py