Metadata-Version: 1.1
Name: cybuffer
Version: 0.1.0
Summary: A Python 2/3 compatible buffer in Cython
Home-page: https://github.com/jakirkham/cybuffer
Author: John Kirkham
Author-email: kirkhamj@janelia.hhmi.org
License: BSD license
Keywords: cybuffer
Platform: UNKNOWN
Classifier: Development Status :: 2 - Pre-Alpha
Classifier: Intended Audience :: Developers
Classifier: License :: OSI Approved :: BSD License
Classifier: Natural Language :: English
Classifier: Programming Language :: Python :: 2
Classifier: Programming Language :: Python :: 2.7
Classifier: Programming Language :: Python :: 3
Classifier: Programming Language :: Python :: 3.5
Classifier: Programming Language :: Python :: 3.6
Classifier: Programming Language :: Python :: 3.7
